.coveragerc
.travis.yml
CHANGES.rst
CONTRIBUTORS.rst
MANIFEST.in
README.rst
bootstrap.py
buildout.cfg
setup.py
travis.cfg
docs/LICENSE.GPL
docs/LICENSE.rst
src/imio/__init__.py
src/imio.project.soap2pm.egg-info/PKG-INFO
src/imio.project.soap2pm.egg-info/SOURCES.txt
src/imio.project.soap2pm.egg-info/dependency_links.txt
src/imio.project.soap2pm.egg-info/entry_points.txt
src/imio.project.soap2pm.egg-info/namespace_packages.txt
src/imio.project.soap2pm.egg-info/not-zip-safe
src/imio.project.soap2pm.egg-info/requires.txt
src/imio.project.soap2pm.egg-info/top_level.txt
src/imio/project/__init__.py
src/imio/project/soap2pm/__init__.py
src/imio/project/soap2pm/adapters.py
src/imio/project/soap2pm/configure.zcml
src/imio/project/soap2pm/interfaces.py
src/imio/project/soap2pm/setuphandlers.py
src/imio/project/soap2pm/testing.py
src/imio/project/soap2pm/testing.zcml
src/imio/project/soap2pm/browser/__init__.py
src/imio/project/soap2pm/browser/configure.zcml
src/imio/project/soap2pm/browser/views.py
src/imio/project/soap2pm/browser/static/.gitkeep
src/imio/project/soap2pm/profiles/default/browserlayer.xml
src/imio/project/soap2pm/profiles/default/imioprojectsoap2pm_marker.txt
src/imio/project/soap2pm/profiles/default/metadata.xml
src/imio/project/soap2pm/profiles/testing/metadata.xml
src/imio/project/soap2pm/tests/__init__.py
src/imio/project/soap2pm/tests/test_robot.py
src/imio/project/soap2pm/tests/test_setup.py
src/imio/project/soap2pm/tests/robot/.gitkeep