Metadata-Version: 2.1
Name: imio.project.soap2pm
Version: 0.2
Summary: Soap client methods
Home-page: http://pypi.python.org/pypi/imio.project.soap2pm
Author: sgeulette
Author-email: support@imio.be
License: GPL
Platform: UNKNOWN
Classifier: Environment :: Web Environment
Classifier: Framework :: Plone
Classifier: Framework :: Plone :: 4.3
Classifier: Programming Language :: Python
Classifier: Programming Language :: Python :: 2.7
Provides-Extra: test
